change_finder/__init__.py
change_finder-0.0.2.dist-info/DESCRIPTION.rst
change_finder-0.0.2.dist-info/METADATA
change_finder-0.0.2.dist-info/RECORD
change_finder-0.0.2.dist-info/WHEEL
change_finder-0.0.2.dist-info/metadata.json
change_finder-0.0.2.dist-info/top_level.txt
